osh/__init__.py
osh/logger.py
osh/time_machine.py
oshtools-0.1.7.dist-info/licenses/LICENSE
oshtools-0.1.7.dist-info/METADATA
oshtools-0.1.7.dist-info/WHEEL
oshtools-0.1.7.dist-info/top_level.txt
oshtools-0.1.7.dist-info/RECORD
