Metadata-Version: 2.4
Name: oshtools
Version: 0.1.7
Summary: A simple Python logging library for chat applications
Author-email: zion <atibjawad@gmail.com>
License: MIT
Project-URL: Homepage, https://github.com/zion-off/oshtools
Project-URL: Repository, https://github.com/zion-off/oshtools
Project-URL: Issues, https://github.com/zion-off/oshtools/issues
Keywords: llm,chat,logging,gcp,google-cloud,logger
Classifier: Development Status :: 4 - Beta
Classifier: Intended Audience :: Developers
Classifier: License :: OSI Approved :: MIT License
Classifier: Operating System :: OS Independent
Classifier: Programming Language :: Python :: 3
Classifier: Programming Language :: Python :: 3.8
Classifier: Programming Language :: Python :: 3.9
Classifier: Programming Language :: Python :: 3.10
Classifier: Programming Language :: Python :: 3.11
Classifier: Programming Language :: Python :: 3.12
Classifier: Topic :: Software Development :: Libraries :: Python Modules
Classifier: Topic :: System :: Logging
Requires-Python: >=3.8
License-File: LICENSE
Provides-Extra: gcp
Requires-Dist: google-cloud-logging>=3.0.0; extra == "gcp"
Provides-Extra: dev
Requires-Dist: pytest>=7.0.0; extra == "dev"
Requires-Dist: black>=23.0.0; extra == "dev"
Requires-Dist: isort>=5.0.0; extra == "dev"
Requires-Dist: flake8>=6.0.0; extra == "dev"
Dynamic: license-file
